{
  "indicators": [
    {
      "id": 1,
      "label": "Sauvegarde doc",
      "typ": "backup",
      "status": "danger",
      "groupId": 1,
      "forced": false,
      "details": "Error 234/ danger"
    },
    {
      "id": 2,
      "label": "Sauvegarde fond ",
      "typ": "backup",
      "status": "warning",
      "groupId": 1,
      "forced": true,
      "details": "Error 0420/ warning"
    },
    {
      "id": 3,
      "label": "Sauvegarde fond ",
      "typ": "backup",
      "status": "warning",
      "groupId": 1,
      "forced": true,
      "details": "Error 324: warning"
    },
    {
      "id": 4,
      "label": "fond doc2",
      "typ": "backup",
      "status": "success",
      "groupId": 1,
      "forced": false,
      "details": "No Error  "
    },
    {
      "id": 5,
      "label": "Sauvegarde",
      "typ": "crontask",
      "status": "danger",
      "groupId": 1,
      "forced": true,
      "details": "Danger zone Error  "
    },
    {
      "id": 6,
      "label": "doc Martens",
      "typ": "crontask",
      "status": "danger",
      "groupId": 2,
      "forced": false,
      "details": "danger Error "
    },
    {
      "id": 7,
      "label": "doc who",
      "typ": "backup",
      "status": "success",
      "groupId": 3,
      "forced": false,
      "details": "No Error  "
    },
    {
      "id": 1456,
      "label": "Sauvegarde doc",
      "typ": "backup",
      "status": "success",
      "groupId": 1,
      "forced": false,
      "details": "Error 234/ danger"
    }
  ],
  "groups": [
    {
      "id": 1,
      "name": "PPP"
    },
    {
      "id": 2,
      "name": "Splicy"
    },
    {
      "id": 3,
      "name": "Mc"
    },
    {
      "id": 4,
      "name": "The India"
    }
  ]
}
